{
    "data": {
        "created_time": "2015-06-02T04:07:01+0000", 
        "id": "10152861401790079_10152861408190079", 
        "message": ""
    }, 
    "reactions": {
        "angry": {
            "data": [], 
            "summary": {
                "total_count": 0
            }
        }, 
        "haha": {
            "data": [], 
            "summary": {
                "total_count": 0
            }
        }, 
        "like": {
            "data": [], 
            "summary": {
                "total_count": 165
            }
        }, 
        "love": {
            "data": [], 
            "summary": {
                "total_count": 0
            }
        }, 
        "sad": {
            "data": [], 
            "summary": {
                "total_count": 0
            }
        }, 
        "wow": {
            "data": [], 
            "summary": {
                "total_count": 0
            }
        }
    }, 
    "replies": [
        {
            "created_time": "2015-06-02T04:12:11+0000", 
            "id": "10152861401790079_10152861414185079", 
            "message": "Turn it up bro\ud83d\ude02\ud83d\ude02"
        }, 
        {
            "created_time": "2015-06-02T04:14:18+0000", 
            "id": "10152861401790079_10152861416200079", 
            "message": "Charge your phone"
        }, 
        {
            "created_time": "2015-06-02T04:14:38+0000", 
            "id": "10152861401790079_10152861416470079", 
            "message": "wrong rappers bro XD"
        }, 
        {
            "created_time": "2015-06-02T04:15:24+0000", 
            "id": "10152861401790079_10152861416880079", 
            "message": "Waya mean? Cody"
        }, 
        {
            "created_time": "2015-06-02T04:19:26+0000", 
            "id": "10152861401790079_10152861420360079", 
            "message": "Elton Kass he has your problem as well \ud83d\ude02\ud83d\ude02 Don't remember Big Sean on this song"
        }, 
        {
            "created_time": "2015-06-02T04:20:07+0000", 
            "id": "10152861401790079_10152861420795079", 
            "message": "Dane-Lucas Kovacevic someone knows my feels"
        }, 
        {
            "created_time": "2015-06-02T04:20:30+0000", 
            "id": "10152861401790079_10152861421010079", 
            "message": "Austin- Cody means you have 9% battery power left."
        }, 
        {
            "created_time": "2015-06-02T04:21:23+0000", 
            "id": "10152861401790079_10152861422045079", 
            "message": "That's what Kenneth said though."
        }, 
        {
            "created_time": "2015-06-02T04:22:22+0000", 
            "id": "10152861401790079_10152861423780079", 
            "message": "Oops....got the comment line/order & name confused, since they are right next to each other."
        }, 
        {
            "created_time": "2015-06-02T04:27:23+0000", 
            "id": "10152861401790079_10152861427465079", 
            "message": "Need this in the UK iTunes \ud83d\ude29\ud83d\ude29\ud83d\ude29\ud83d\ude29"
        }, 
        {
            "created_time": "2015-06-02T04:57:59+0000", 
            "id": "10152861401790079_10152861455995079", 
            "message": "If your a fan you would spend $1.29 come on now."
        }, 
        {
            "created_time": "2015-06-02T04:58:41+0000", 
            "id": "10152861401790079_10152861456395079", 
            "message": "I did spend $1.29 Gabriel Luera"
        }, 
        {
            "created_time": "2015-06-02T05:07:23+0000", 
            "id": "10152861401790079_10152861463795079", 
            "message": "Just bought it!\ud83d\ude1c\ud83d\ude1c"
        }, 
        {
            "created_time": "2015-06-02T05:11:01+0000", 
            "id": "10152861401790079_10152861474400079", 
            "message": "I didn't hear Big Sean or Royce on it."
        }, 
        {
            "created_time": "2015-06-02T05:13:02+0000", 
            "id": "10152861401790079_10152861477575079", 
            "message": "It's messed up. My Music app is."
        }, 
        {
            "created_time": "2015-06-02T05:14:18+0000", 
            "id": "10152861401790079_10152861478900079", 
            "message": "Gabriel Luera"
        }, 
        {
            "created_time": "2015-06-02T05:19:17+0000", 
            "id": "10152861401790079_10152861482235079", 
            "message": "So I can't find it.. Not available for Australia?? \ud83d\ude14"
        }, 
        {
            "created_time": "2015-06-02T05:31:02+0000", 
            "id": "10152861401790079_10152861490120079", 
            "message": "Not avaible in New Zealand , typical."
        }, 
        {
            "created_time": "2015-06-02T05:34:14+0000", 
            "id": "10152861401790079_10152861492175079", 
            "message": "bitchs"
        }, 
        {
            "created_time": "2015-06-02T05:45:42+0000", 
            "id": "10152861401790079_10152861540050079", 
            "message": "http://eminemnews.net/wp-content/uploads/2015/06/Eminem-Phenomenal-Audio-Only.mp3"
        }, 
        {
            "created_time": "2015-06-02T07:42:27+0000", 
            "id": "10152861401790079_10152861668715079", 
            "message": "Damn, you really wasted your money?"
        }, 
        {
            "created_time": "2015-06-02T07:43:53+0000", 
            "id": "10152861401790079_10152861669550079", 
            "message": "My music app is messed up too"
        }, 
        {
            "created_time": "2015-06-02T08:14:17+0000", 
            "id": "10152861401790079_10152861690235079", 
            "message": "Neither in Holland yet \ud83d\ude22"
        }, 
        {
            "created_time": "2015-06-02T08:37:08+0000", 
            "id": "10152861401790079_10152861704340079", 
            "message": "Kieran Feck ^^^^"
        }, 
        {
            "created_time": "2015-06-02T09:28:55+0000", 
            "id": "10152861401790079_10152861765150079", 
            "message": "It's not available in UK yet either :( \ufe0fXx"
        }
    ]
}