{
    "data": {
        "created_time": "2017-10-19T13:34:03+0000", 
        "id": "10154880628245079_359580531155417", 
        "message": "This suppose to be a post about the Pistions making their return back to Detroit.  The city is making a come back and everyone wants to make this a political post and fight about it. Y'all need to spread some love"
    }, 
    "reactions": {
        "angry": {
            "data": [], 
            "summary": {
                "total_count": 0
            }
        }, 
        "haha": {
            "data": [], 
            "summary": {
                "total_count": 0
            }
        }, 
        "like": {
            "data": [], 
            "summary": {
                "total_count": 0
            }
        }, 
        "love": {
            "data": [], 
            "summary": {
                "total_count": 0
            }
        }, 
        "sad": {
            "data": [], 
            "summary": {
                "total_count": 0
            }
        }, 
        "wow": {
            "data": [], 
            "summary": {
                "total_count": 0
            }
        }
    }, 
    "replies": []
}