{
    "data": {
        "created_time": "2017-10-19T01:21:27+0000", 
        "id": "10154880628245079_926482640832162", 
        "message": "I'm a trump supporter. Em is my favorite artist of all time. I dont care about what he said because he has his opinion to say so. I love Eminem because he speaks his mind. You can't hate someone for having a different political standpoint. Everyone thinks differently and it's how you choose to act towards that."
    }, 
    "reactions": {
        "angry": {
            "data": [], 
            "summary": {
                "total_count": 0
            }
        }, 
        "haha": {
            "data": [], 
            "summary": {
                "total_count": 0
            }
        }, 
        "like": {
            "data": [], 
            "summary": {
                "total_count": 23
            }
        }, 
        "love": {
            "data": [], 
            "summary": {
                "total_count": 4
            }
        }, 
        "sad": {
            "data": [], 
            "summary": {
                "total_count": 0
            }
        }, 
        "wow": {
            "data": [], 
            "summary": {
                "total_count": 0
            }
        }
    }, 
    "replies": [
        {
            "created_time": "2017-10-19T02:52:30+0000", 
            "id": "10154880628245079_926510444162715", 
            "message": "ditto that!!!"
        }, 
        {
            "created_time": "2017-10-19T03:19:36+0000", 
            "id": "10154880628245079_389136388186706", 
            "message": "the cognitive dissonance when liking Trump and Eminem ... to me intellectually it's impossible ... I am with slim shady in that case"
        }, 
        {
            "created_time": "2017-10-19T07:04:09+0000", 
            "id": "10154880628245079_1950911941818015", 
            "message": "I respect your attitude, but I don't understand how anyone would still support Trump.  He's obviously an objectively shitty person, and I think it's gotten pretty painfully clear to Almost everyone how incompetent he truly is."
        }, 
        {
            "created_time": "2017-10-19T09:30:03+0000", 
            "id": "10154880628245079_1659115934138673", 
            "message": "Honestly it's hypocritical to say it's okay for him to have a different political opinion when his opinion is \"fuck you if you don't agree with me\". Sounds a bit fascist but it's okay because it's his opinion right?"
        }, 
        {
            "created_time": "2017-10-19T13:31:48+0000", 
            "id": "10154880628245079_1972463169694272", 
            "message": "i think em is wrong, evenif u have a different opinion, u can't tel me fuck..."
        }, 
        {
            "created_time": "2017-10-19T15:53:22+0000", 
            "id": "10154880628245079_501618743539201", 
            "message": "If you go back to when Em was just starting out, he has made MANY remarks about so many issues.  To say oh, I'm not listening to him anymore cause he spoke about Trump, dam ppl, know your priorities,  everyone has a right to their opinions, keep it moving and put some preparation H on your butt."
        }, 
        {
            "created_time": "2017-11-04T13:30:32+0000", 
            "id": "10154880628245079_124650221539974", 
            "message": "fu\u00a9k trump"
        }
    ]
}