{
    "data": {
        "created_time": "2017-02-04T13:00:00+0000", 
        "id": "10155479830046729_10155003302984464", 
        "message": "How duo I get my own friendship video"
    }, 
    "reactions": {
        "angry": {
            "data": [], 
            "summary": {
                "total_count": 0
            }
        }, 
        "haha": {
            "data": [], 
            "summary": {
                "total_count": 0
            }
        }, 
        "like": {
            "data": [], 
            "summary": {
                "total_count": 1
            }
        }, 
        "love": {
            "data": [], 
            "summary": {
                "total_count": 0
            }
        }, 
        "sad": {
            "data": [], 
            "summary": {
                "total_count": 0
            }
        }, 
        "wow": {
            "data": [], 
            "summary": {
                "total_count": 0
            }
        }
    }, 
    "replies": [
        {
            "created_time": "2017-02-04T13:17:40+0000", 
            "id": "10155479830046729_10154394796441985", 
            "message": "Hi, Rub\u00ef. Friends Day videos will be available to people with enough content to create a compelling and quality video. These videos will start to roll out January 31 through February 4. -Rhea"
        }, 
        {
            "created_time": "2017-02-04T13:42:10+0000", 
            "id": "10155479830046729_10155003396354464", 
            "message": "Aww. I see. I guess I didn't get one.\n\ud83d\ude22 \nThank you for responding"
        }
    ]
}