{
    "data": {
        "created_time": "2016-03-19T21:18:28+0000", 
        "id": "10153406289190079_10153406296055079", 
        "message": "come on Turkey Eminem but i dont wanna Shady i wanna Eminem we like shady but we Love EM\u0130NEM Turkey wait for you Come one more time 3 days of this world im a rapper and your dreams see your favorite rappers and my dreams see u therefore come on man !!!!1111!!111! oh fuck I wrote a novel..."
    }, 
    "reactions": {
        "angry": {
            "data": [], 
            "summary": {
                "total_count": 0
            }
        }, 
        "haha": {
            "data": [], 
            "summary": {
                "total_count": 0
            }
        }, 
        "like": {
            "data": [], 
            "summary": {
                "total_count": 3
            }
        }, 
        "love": {
            "data": [], 
            "summary": {
                "total_count": 0
            }
        }, 
        "sad": {
            "data": [], 
            "summary": {
                "total_count": 0
            }
        }, 
        "wow": {
            "data": [], 
            "summary": {
                "total_count": 0
            }
        }
    }, 
    "replies": [
        {
            "created_time": "2016-03-19T22:47:20+0000", 
            "id": "10153406289190079_10153406466210079", 
            "message": "Stay safe! #prayforturkey"
        }
    ]
}