{
    "data": {
        "created_time": "2015-03-09T20:50:53+0000", 
        "id": "10152677289405079_10152677362050079", 
        "message": ""
    }, 
    "reactions": {
        "angry": {
            "data": [], 
            "summary": {
                "total_count": 0
            }
        }, 
        "haha": {
            "data": [], 
            "summary": {
                "total_count": 0
            }
        }, 
        "like": {
            "data": [], 
            "summary": {
                "total_count": 61
            }
        }, 
        "love": {
            "data": [], 
            "summary": {
                "total_count": 0
            }
        }, 
        "sad": {
            "data": [], 
            "summary": {
                "total_count": 0
            }
        }, 
        "wow": {
            "data": [], 
            "summary": {
                "total_count": 0
            }
        }
    }, 
    "replies": [
        {
            "created_time": "2015-03-09T21:34:04+0000", 
            "id": "10152677289405079_10152677431960079", 
            "message": "Was it just me or did anyone else read that like the last few words of rap god \ud83d\ude02"
        }, 
        {
            "created_time": "2015-03-10T00:57:04+0000", 
            "id": "10152677289405079_10152677739300079", 
            "message": "Thats the point"
        }
    ]
}