{
    "data": {
        "created_time": "2015-10-26T18:16:48+0000", 
        "id": "10154150471191729_10154152445176729", 
        "message": "thanks a alot \nFacebook for ever ^_^"
    }, 
    "reactions": {
        "angry": {
            "data": [], 
            "summary": {
                "total_count": 0
            }
        }, 
        "haha": {
            "data": [], 
            "summary": {
                "total_count": 0
            }
        }, 
        "like": {
            "data": [], 
            "summary": {
                "total_count": 3
            }
        }, 
        "love": {
            "data": [], 
            "summary": {
                "total_count": 0
            }
        }, 
        "sad": {
            "data": [], 
            "summary": {
                "total_count": 0
            }
        }, 
        "wow": {
            "data": [], 
            "summary": {
                "total_count": 0
            }
        }
    }, 
    "replies": [
        {
            "created_time": "2015-10-26T19:35:08+0000", 
            "id": "10154150471191729_10154152593931729", 
            "message": "You're welcome, Sonia. Thanks for the kind words! -Rey"
        }, 
        {
            "created_time": "2015-10-26T19:38:08+0000", 
            "id": "10154150471191729_10154152598626729", 
            "message": "woooow Thanks for reply"
        }
    ]
}