{
    "data": {
        "created_time": "2017-11-04T00:32:34+0000", 
        "id": "10154914644810079_134251487295955", 
        "message": "If his little rap he did for Trump made sense I wouldn't  have a problem, but it didnt. It didn't make any sense and it absolutely sucked. His worst ever."
    }, 
    "reactions": {
        "angry": {
            "data": [], 
            "summary": {
                "total_count": 0
            }
        }, 
        "haha": {
            "data": [], 
            "summary": {
                "total_count": 0
            }
        }, 
        "like": {
            "data": [], 
            "summary": {
                "total_count": 1
            }
        }, 
        "love": {
            "data": [], 
            "summary": {
                "total_count": 0
            }
        }, 
        "sad": {
            "data": [], 
            "summary": {
                "total_count": 0
            }
        }, 
        "wow": {
            "data": [], 
            "summary": {
                "total_count": 0
            }
        }
    }, 
    "replies": []
}