{
    "data": {
        "created_time": "2015-06-30T00:35:27+0000", 
        "id": "10152921774870079_10152921788890079", 
        "message": "Eminem You made this Phenomenal"
    }, 
    "reactions": {
        "angry": {
            "data": [], 
            "summary": {
                "total_count": 0
            }
        }, 
        "haha": {
            "data": [], 
            "summary": {
                "total_count": 0
            }
        }, 
        "like": {
            "data": [], 
            "summary": {
                "total_count": 457
            }
        }, 
        "love": {
            "data": [], 
            "summary": {
                "total_count": 0
            }
        }, 
        "sad": {
            "data": [], 
            "summary": {
                "total_count": 0
            }
        }, 
        "wow": {
            "data": [], 
            "summary": {
                "total_count": 0
            }
        }
    }, 
    "replies": [
        {
            "created_time": "2015-06-30T04:47:38+0000", 
            "id": "10152921774870079_10152922164755079", 
            "message": ""
        }, 
        {
            "created_time": "2015-06-30T06:43:42+0000", 
            "id": "10152921774870079_10152922275365079", 
            "message": "Carlos Reyes Cadena"
        }, 
        {
            "created_time": "2015-06-30T14:30:44+0000", 
            "id": "10152921774870079_10152922918930079", 
            "message": "Abdul Rahman Basil\ud83d\ude0d\u064a\u062e\u0628\u0644"
        }, 
        {
            "created_time": "2015-06-30T20:33:53+0000", 
            "id": "10152921774870079_10152923499825079", 
            "message": "https://www.youtube.com/watch?v=Wy1k_I6jzkw"
        }
    ]
}