{
    "data": {
        "created_time": "2012-12-11T17:57:25+0000", 
        "id": "45309870078_10151164675350079", 
        "message": "Watch the official music video for Skylar Grey's song \"C'mon Let Me Ride\" ft. Eminem here: http://bit.ly/VANwZX.  \r\n\r\nBuy the song here: http://smarturl.it/CmonLetMeRide"
    }, 
    "reactions": {
        "angry": {
            "data": [], 
            "summary": {
                "total_count": 0
            }
        }, 
        "haha": {
            "data": [], 
            "summary": {
                "total_count": 2
            }
        }, 
        "like": {
            "data": [], 
            "summary": {
                "total_count": 195985
            }
        }, 
        "love": {
            "data": [], 
            "summary": {
                "total_count": 50
            }
        }, 
        "sad": {
            "data": [], 
            "summary": {
                "total_count": 0
            }
        }, 
        "wow": {
            "data": [], 
            "summary": {
                "total_count": 1
            }
        }
    }
}