{
    "data": {
        "created_time": "2016-07-24T19:56:45+0000", 
        "id": "10153631964475079_1217405808318729", 
        "message": "Mad song carnt go wrog I think I will have another bong one my own laying lo  now ill have a shot of some good ice drink some bourbon and eat my rice go gamble throw the dice look ive just won enough to by exter c and a pound to smok and shout arond and pjck up my guitar and play a tune or the sound to sing this song and do it all again smoking the rest of my cones and trying to smoke another bong im so fucking high nowthis song carrnt go wrong mnm can you finish this song its yours"
    }, 
    "reactions": {
        "angry": {
            "data": [], 
            "summary": {
                "total_count": 0
            }
        }, 
        "haha": {
            "data": [], 
            "summary": {
                "total_count": 0
            }
        }, 
        "like": {
            "data": [], 
            "summary": {
                "total_count": 0
            }
        }, 
        "love": {
            "data": [], 
            "summary": {
                "total_count": 0
            }
        }, 
        "sad": {
            "data": [], 
            "summary": {
                "total_count": 0
            }
        }, 
        "wow": {
            "data": [], 
            "summary": {
                "total_count": 0
            }
        }
    }, 
    "replies": []
}