{
    "data": {
        "created_time": "2017-11-11T12:29:14+0000", 
        "id": "10156725574856729_10156727336316729", 
        "message": "Happy Veterans day to all the men and women for serving are country may God bless each and everyone if you"
    }, 
    "reactions": {
        "angry": {
            "data": [], 
            "summary": {
                "total_count": 0
            }
        }, 
        "haha": {
            "data": [], 
            "summary": {
                "total_count": 0
            }
        }, 
        "like": {
            "data": [], 
            "summary": {
                "total_count": 8
            }
        }, 
        "love": {
            "data": [], 
            "summary": {
                "total_count": 1
            }
        }, 
        "sad": {
            "data": [], 
            "summary": {
                "total_count": 0
            }
        }, 
        "wow": {
            "data": [], 
            "summary": {
                "total_count": 0
            }
        }
    }, 
    "replies": []
}