{
    "data": {
        "created_time": "2016-02-05T11:29:08+0000", 
        "id": "10154374733446729_10154378223416729", 
        "message": "Thank you So much Facebook! I learn that friends are matter to me... !!!!! Happy friends DAY Facebook!! \ud83d\ude0a\ud83d\ude0a\ud83d\ude0d\ud83d\udc6d\ud83d\udc6c"
    }, 
    "reactions": {
        "angry": {
            "data": [], 
            "summary": {
                "total_count": 0
            }
        }, 
        "haha": {
            "data": [], 
            "summary": {
                "total_count": 0
            }
        }, 
        "like": {
            "data": [], 
            "summary": {
                "total_count": 0
            }
        }, 
        "love": {
            "data": [], 
            "summary": {
                "total_count": 0
            }
        }, 
        "sad": {
            "data": [], 
            "summary": {
                "total_count": 0
            }
        }, 
        "wow": {
            "data": [], 
            "summary": {
                "total_count": 0
            }
        }
    }, 
    "replies": []
}