{
    "data": {
        "created_time": "2009-12-16T04:00:58+0000",
        "id": "208804506121_8381420",
        "message": "i love u so much! and i need u in mexico right now :'( <3 "
    },
    "reactions": {
        "angry": {
            "data": [],
            "summary": {
                "total_count": 0
            }
        },
        "haha": {
            "data": [],
            "summary": {
                "total_count": 0
            }
        },
        "like": {
            "data": [],
            "summary": {
                "total_count": 0
            }
        },
        "love": {
            "data": [],
            "summary": {
                "total_count": 0
            }
        },
        "sad": {
            "data": [],
            "summary": {
                "total_count": 0
            }
        },
        "wow": {
            "data": [],
            "summary": {
                "total_count": 0
            }
        }
    },
    "replies": []
}