{
    "data": {
        "created_time": "2016-10-12T16:46:10+0000", 
        "id": "10155085288566729_10155088013971729", 
        "message": "You know Facebook you simply the best an outstanding"
    }, 
    "reactions": {
        "angry": {
            "data": [], 
            "summary": {
                "total_count": 0
            }
        }, 
        "haha": {
            "data": [], 
            "summary": {
                "total_count": 0
            }
        }, 
        "like": {
            "data": [], 
            "summary": {
                "total_count": 0
            }
        }, 
        "love": {
            "data": [], 
            "summary": {
                "total_count": 0
            }
        }, 
        "sad": {
            "data": [], 
            "summary": {
                "total_count": 0
            }
        }, 
        "wow": {
            "data": [], 
            "summary": {
                "total_count": 0
            }
        }
    }, 
    "replies": [
        {
            "created_time": "2016-10-12T17:30:33+0000", 
            "id": "10155085288566729_10155088145076729", 
            "message": "Hey Cheryl. We appreciate the kind words. Thanks for sharing! -Kate"
        }, 
        {
            "created_time": "2016-10-12T17:43:52+0000", 
            "id": "10155085288566729_10155088202251729", 
            "message": ""
        }, 
        {
            "created_time": "2016-10-12T17:44:16+0000", 
            "id": "10155085288566729_10155088203746729", 
            "message": "U welcome"
        }
    ]
}