{
    "data": {
        "created_time": "2014-06-24T19:02:07+0000", 
        "id": "10152831662891729_10152841840626729", 
        "message": "Why has my Facebook app on my Tablet stopped working? 3rd day now and I keep getting a message without anything loading saying Facebook has stopped working!! I send in a report each time and no help!! What the heck is going on??"
    }, 
    "reactions": {
        "angry": {
            "data": [], 
            "summary": {
                "total_count": 0
            }
        }, 
        "haha": {
            "data": [], 
            "summary": {
                "total_count": 0
            }
        }, 
        "like": {
            "data": [], 
            "summary": {
                "total_count": 5
            }
        }, 
        "love": {
            "data": [], 
            "summary": {
                "total_count": 0
            }
        }, 
        "sad": {
            "data": [], 
            "summary": {
                "total_count": 0
            }
        }, 
        "wow": {
            "data": [], 
            "summary": {
                "total_count": 0
            }
        }
    }, 
    "replies": [
        {
            "created_time": "2014-06-24T19:28:40+0000", 
            "id": "10152831662891729_10152841890076729", 
            "message": "Hey Natalie. We\u2019re sorry to hear that you\u2019re experiencing issues with your tablet Facebook application. Please help us track this issue by reporting it in our Help Center. http://on.fb.me/18dEFaD -Sarah"
        }, 
        {
            "created_time": "2014-06-24T20:33:13+0000", 
            "id": "10152831662891729_10152842027446729", 
            "message": "Stop"
        }, 
        {
            "created_time": "2014-06-24T23:56:50+0000", 
            "id": "10152831662891729_10152842428671729", 
            "message": "It's the Facebook for android and those options in the link don't help bc i can't take a screen shot!! Have u been hearing about this issue the past few days??"
        }, 
        {
            "created_time": "2014-07-10T22:20:37+0000", 
            "id": "10152831662891729_10152880920461729", 
            "message": "In case you haven't tried, did you restart it?  I had that problem with my android tablet before, several times actually, and it might have gotten an update and just needed to be restarted....."
        }
    ]
}