{
    "data": {
        "created_time": "2015-02-05T18:44:23+0000", 
        "id": "10152612136485079_10152612166530079", 
        "message": ""
    }, 
    "reactions": {
        "angry": {
            "data": [], 
            "summary": {
                "total_count": 0
            }
        }, 
        "haha": {
            "data": [], 
            "summary": {
                "total_count": 0
            }
        }, 
        "like": {
            "data": [], 
            "summary": {
                "total_count": 44
            }
        }, 
        "love": {
            "data": [], 
            "summary": {
                "total_count": 0
            }
        }, 
        "sad": {
            "data": [], 
            "summary": {
                "total_count": 0
            }
        }, 
        "wow": {
            "data": [], 
            "summary": {
                "total_count": 0
            }
        }
    }, 
    "replies": [
        {
            "created_time": "2015-02-15T12:41:19+0000", 
            "id": "10152612136485079_10152632481765079", 
            "message": "he's ageing so much."
        }, 
        {
            "created_time": "2015-02-20T05:46:51+0000", 
            "id": "10152612136485079_10152643223115079", 
            "message": "Jim Jammy"
        }, 
        {
            "created_time": "2015-02-20T05:47:19+0000", 
            "id": "10152612136485079_10152643223375079", 
            "message": "You have to wear a rubber, or you've become a motherfucker..."
        }
    ]
}