{
    "data": {
        "created_time": "2016-12-10T20:48:28+0000", 
        "id": "10155278547321729_1806918456256596", 
        "message": "Thanks Facebook for keeping me connected to family and friends especially those far away ...love the video!!!"
    }, 
    "reactions": {
        "angry": {
            "data": [], 
            "summary": {
                "total_count": 0
            }
        }, 
        "haha": {
            "data": [], 
            "summary": {
                "total_count": 0
            }
        }, 
        "like": {
            "data": [], 
            "summary": {
                "total_count": 35
            }
        }, 
        "love": {
            "data": [], 
            "summary": {
                "total_count": 0
            }
        }, 
        "sad": {
            "data": [], 
            "summary": {
                "total_count": 0
            }
        }, 
        "wow": {
            "data": [], 
            "summary": {
                "total_count": 0
            }
        }
    }, 
    "replies": [
        {
            "created_time": "2016-12-10T21:11:44+0000", 
            "id": "10155278547321729_1614352298867549", 
            "message": "We're glad you're able to stay connected, Vicki! -Zack"
        }, 
        {
            "created_time": "2016-12-11T23:50:11+0000", 
            "id": "10155278547321729_1611531789156705", 
            "message": "Facebook how do I make a friend video on my friendship anniversary I never get the option smhhhh"
        }, 
        {
            "created_time": "2016-12-12T02:58:23+0000", 
            "id": "10155278547321729_1204060379670394", 
            "message": "Thank you Facebook"
        }, 
        {
            "created_time": "2016-12-12T09:26:44+0000", 
            "id": "10155278547321729_1611686475807903", 
            "message": "Wow!!! We get so caught up in it we don't always stop to reflect. May we remember the good times, forgive the bad and welcome 2017 with gusto."
        }, 
        {
            "created_time": "2016-12-12T10:54:24+0000", 
            "id": "10155278547321729_981820865257840", 
            "message": "Yes ty FB for the short review of 2016 blessed year for sure  for friends&family thanks ppl being here amen!"
        }, 
        {
            "created_time": "2016-12-12T11:29:00+0000", 
            "id": "10155278547321729_697735963742208", 
            "message": "Very nice, Fb! I am happy whit my year review v\u00eddeo! - Cary"
        }, 
        {
            "created_time": "2016-12-12T11:39:01+0000", 
            "id": "10155278547321729_1242112949181001", 
            "message": "Thanks for the review for 2016! I love it!"
        }, 
        {
            "created_time": "2016-12-12T11:45:05+0000", 
            "id": "10155278547321729_1169670496444084", 
            "message": "Loving my review good job."
        }, 
        {
            "created_time": "2016-12-12T11:50:47+0000", 
            "id": "10155278547321729_1348478158507259", 
            "message": "I use to start my mornings with the local news, since I connected to Facebook I start my mornings connecting with friends and family. Thank you facebook for reducing anxiety and increasing optimisim. Thank Facebook for another year."
        }, 
        {
            "created_time": "2016-12-12T11:55:32+0000", 
            "id": "10155278547321729_1151737798274731", 
            "message": "I love Facebook. As a senior, Facebook and television keeps me connected to the outside world. I'd be so lonely without either one."
        }
    ]
}