{
    "data": {
        "created_time": "2014-11-12T09:03:56+0000", 
        "id": "10152427885210079_10152428214970079", 
        "message": "Hahaha Emmanuel get out of your fantasy world! I would rip your tongue out and feed it to you partna!! I believe it's racist to believe just cause you're black you are superior to Whites. I suppose that's not in your eyes though cause only white people can be racist, right??"
    }, 
    "reactions": {
        "angry": {
            "data": [], 
            "summary": {
                "total_count": 0
            }
        }, 
        "haha": {
            "data": [], 
            "summary": {
                "total_count": 0
            }
        }, 
        "like": {
            "data": [], 
            "summary": {
                "total_count": 1
            }
        }, 
        "love": {
            "data": [], 
            "summary": {
                "total_count": 0
            }
        }, 
        "sad": {
            "data": [], 
            "summary": {
                "total_count": 0
            }
        }, 
        "wow": {
            "data": [], 
            "summary": {
                "total_count": 0
            }
        }
    }, 
    "replies": [
        {
            "created_time": "2014-11-12T09:13:22+0000", 
            "id": "10152427885210079_10152428222350079", 
            "message": "If he's racist why is he my friend?  Man, just quit while you're behind..he'd flatten you, verbally and physically if you challenged him which I would not want to see as you Eminem acolytes only know foul language and violence like brutes.  Listen to The Bad Brains if you want a real pertinent message."
        }, 
        {
            "created_time": "2014-11-12T09:15:16+0000", 
            "id": "10152427885210079_10152428223360079", 
            "message": "Cause you are against a white rapper"
        }, 
        {
            "created_time": "2014-11-12T09:17:26+0000", 
            "id": "10152427885210079_10152428224575079", 
            "message": "Your an idiot! If im racist then why was my best friend black???? Huh? Huh? Quit while you where never in the race to begin with."
        }, 
        {
            "created_time": "2014-11-13T03:06:31+0000", 
            "id": "10152427885210079_10152429784290079", 
            "message": "Listen one final time.  I know you are \"special\", but it's not because he's white, it's because he promotes violence against women.  Please learn to spell you're for the last time. Ever heard of Third Bass?  WHITE"
        }
    ]
}