{
    "data": {
        "created_time": "2015-11-19T22:38:10+0000", 
        "id": "10154189880711729_10154202744766729", 
        "message": "Dear Facebook,                                                                                                                                    Can you please make a flag cover for Kenya?                                                       Sincerely, Evelyn"
    }, 
    "reactions": {
        "angry": {
            "data": [], 
            "summary": {
                "total_count": 0
            }
        }, 
        "haha": {
            "data": [], 
            "summary": {
                "total_count": 0
            }
        }, 
        "like": {
            "data": [], 
            "summary": {
                "total_count": 11
            }
        }, 
        "love": {
            "data": [], 
            "summary": {
                "total_count": 0
            }
        }, 
        "sad": {
            "data": [], 
            "summary": {
                "total_count": 0
            }
        }, 
        "wow": {
            "data": [], 
            "summary": {
                "total_count": 0
            }
        }
    }, 
    "replies": [
        {
            "created_time": "2015-11-19T22:41:41+0000", 
            "id": "10154189880711729_10154202749831729", 
            "message": "We appreciate your feedback, Evelyn. We've learned a lot from this launch. We're continuing to explore how we can help people use their Facebook profiles to show their support for the things they care about. If you have any suggestions, please share them with us here: http://on.fb.me/1Yj0NZZ. -Abby"
        }, 
        {
            "created_time": "2015-11-20T12:53:41+0000", 
            "id": "10154189880711729_10154203775301729", 
            "message": "Thank you Evelyn. Kenya should have been the first launch...this tragedy for them happened in April...why just launch Paris first when Kenya's tragedy happened months prior?"
        }, 
        {
            "created_time": "2015-11-21T09:53:30+0000", 
            "id": "10154189880711729_10154205637616729", 
            "message": "Yes, I support there should be a flag every time a massive shooting happens so we can use the flag to support them Please, Good Idea. Facebook should start working on it because yesterday there was an attack in Mali and there is no flag to support. I personally had to make my own by putting it in my picture with paint. Greetings"
        }, 
        {
            "created_time": "2015-11-25T06:17:00+0000", 
            "id": "10154189880711729_10154213688701729", 
            "message": "Terror attacks in Africa is nothing new and happens almost daily. It does not happen often in France which is why it drew so much attention. Find something else about which to complain."
        }, 
        {
            "created_time": "2015-11-26T18:23:15+0000", 
            "id": "10154189880711729_10154216615311729", 
            "message": "how to change profile picture at siriya suport"
        }, 
        {
            "created_time": "2016-06-03T20:24:25+0000", 
            "id": "10154189880711729_1198322526847418", 
            "message": ""
        }, 
        {
            "created_time": "2016-06-03T20:26:03+0000", 
            "id": "10154189880711729_1281863868490764", 
            "message": "Starlight shine bright @"
        }
    ]
}