{
    "data": {
        "created_time": "2014-02-05T05:30:10+0000", 
        "id": "10152511560381729_33973440", 
        "message": "Happy 10th Birthday Facebooooooooooooooooo *gasps for air* oooooooooooooook!!! \ud83c\udf8a\ud83c\udf88\ud83c\udf89\ud83c\udf81\ud83c\udf82"
    }, 
    "reactions": {
        "angry": {
            "data": [], 
            "summary": {
                "total_count": 0
            }
        }, 
        "haha": {
            "data": [], 
            "summary": {
                "total_count": 0
            }
        }, 
        "like": {
            "data": [], 
            "summary": {
                "total_count": 1
            }
        }, 
        "love": {
            "data": [], 
            "summary": {
                "total_count": 0
            }
        }, 
        "sad": {
            "data": [], 
            "summary": {
                "total_count": 0
            }
        }, 
        "wow": {
            "data": [], 
            "summary": {
                "total_count": 0
            }
        }
    }, 
    "replies": []
}