{
    "data": {
        "created_time": "2014-01-23T16:51:06+0000", 
        "id": "10151872618665079_12324964", 
        "message": "Hahaha get it"
    }, 
    "reactions": {
        "angry": {
            "data": [], 
            "summary": {
                "total_count": 0
            }
        }, 
        "haha": {
            "data": [], 
            "summary": {
                "total_count": 0
            }
        }, 
        "like": {
            "data": [], 
            "summary": {
                "total_count": 5946
            }
        }, 
        "love": {
            "data": [], 
            "summary": {
                "total_count": 0
            }
        }, 
        "sad": {
            "data": [], 
            "summary": {
                "total_count": 0
            }
        }, 
        "wow": {
            "data": [], 
            "summary": {
                "total_count": 0
            }
        }
    }, 
    "replies": [
        {
            "created_time": "2014-01-23T17:25:56+0000", 
            "id": "10151872618665079_12325829", 
            "message": "He is not God"
        }, 
        {
            "created_time": "2014-01-23T17:46:39+0000", 
            "id": "10151872618665079_12326161", 
            "message": ""
        }, 
        {
            "created_time": "2014-01-23T18:51:32+0000", 
            "id": "10151872618665079_12327136", 
            "message": ""
        }, 
        {
            "created_time": "2014-01-23T19:45:23+0000", 
            "id": "10151872618665079_12327758", 
            "message": "If you think he is a rap god, you know nothing about hip hop"
        }, 
        {
            "created_time": "2014-01-23T19:55:51+0000", 
            "id": "10151872618665079_12327879", 
            "message": "HAHAHA Leo Perovanovi\u0107 !!!! he is a RAPgod! not a hip hop god..... but he is a god and thats it!"
        }, 
        {
            "created_time": "2014-01-23T20:10:53+0000", 
            "id": "10151872618665079_12328031", 
            "message": "Yes Leo, elitism is a very effective way to get people to listen to you. Tell us why we shouldn't listen to music that we like."
        }, 
        {
            "created_time": "2014-01-23T20:16:06+0000", 
            "id": "10151872618665079_12328083", 
            "message": "leo perovanovic or smh.. if u think he is not a rap god then u aint know nothing about hip hop.."
        }, 
        {
            "created_time": "2014-01-23T20:25:44+0000", 
            "id": "10151872618665079_12328171", 
            "message": ""
        }, 
        {
            "created_time": "2014-01-23T21:43:41+0000", 
            "id": "10151872618665079_12328903", 
            "message": "Eminem nadie mejooor"
        }, 
        {
            "created_time": "2014-01-23T22:00:26+0000", 
            "id": "10151872618665079_12329043", 
            "message": "yep!!!!"
        }, 
        {
            "created_time": "2014-01-23T22:14:27+0000", 
            "id": "10151872618665079_12329126", 
            "message": "rap good if youthink not you no nothing about rab  nobody drops lyrical bombs lkike em maybe technine but shit rapgod kod collab would be fucking sick"
        }, 
        {
            "created_time": "2014-01-23T22:19:13+0000", 
            "id": "10151872618665079_12329160", 
            "message": ""
        }, 
        {
            "created_time": "2014-01-23T22:45:43+0000", 
            "id": "10151872618665079_12329381", 
            "message": "Aybabtu Hehe"
        }, 
        {
            "created_time": "2014-01-23T22:56:26+0000", 
            "id": "10151872618665079_12329463", 
            "message": "Lol"
        }, 
        {
            "created_time": "2014-01-23T23:11:46+0000", 
            "id": "10151872618665079_12329585", 
            "message": "lol thats great!"
        }, 
        {
            "created_time": "2014-01-23T23:12:34+0000", 
            "id": "10151872618665079_12329595", 
            "message": "style :v"
        }, 
        {
            "created_time": "2014-01-23T23:33:55+0000", 
            "id": "10151872618665079_12329740", 
            "message": "Alejandro Quiroz"
        }, 
        {
            "created_time": "2014-01-23T23:35:57+0000", 
            "id": "10151872618665079_12329756", 
            "message": "wtf u talking about jb"
        }, 
        {
            "created_time": "2014-01-23T23:38:15+0000", 
            "id": "10151872618665079_12329778", 
            "message": "hahahah rap god"
        }, 
        {
            "created_time": "2014-01-23T23:47:04+0000", 
            "id": "10151872618665079_12329818", 
            "message": "As much as I like Eminem (being that he's my favorite rapper), I hate looking at an Eminem pic and seeing Stan on everything. Y'all make it hard for us actual fans (not dick riders) to be fans, and fit in with other rap and hip-hop fans."
        }, 
        {
            "created_time": "2014-01-23T23:52:30+0000", 
            "id": "10151872618665079_12329861", 
            "message": "lovin it!!!!!"
        }, 
        {
            "created_time": "2014-01-24T01:07:32+0000", 
            "id": "10151872618665079_12330330", 
            "message": "HA!"
        }, 
        {
            "created_time": "2014-01-24T01:22:15+0000", 
            "id": "10151872618665079_12330441", 
            "message": "Haha XD"
        }, 
        {
            "created_time": "2014-01-24T01:28:19+0000", 
            "id": "10151872618665079_12330471", 
            "message": "LOVE YOU EMINEM!!! you are the total and ultimate rap god! <3 :D"
        }, 
        {
            "created_time": "2014-01-24T01:29:48+0000", 
            "id": "10151872618665079_12330479", 
            "message": "Leo.. Oh Leo, Leo. He doesn't do hip hop, he does pop fused a lot of other genres. Quote (lyrics) from Rap God:\n\n\"\"Oh, he's too mainstream\nWell, that's what they do when they get jealous, they confuse it\nIt's not hip-hop, it's pop\nCause I found a hella way to fuse it\nWith rock, shock rap with Doc\nThrow on \"Lose Yourself\" and make 'em lose it\""
        }
    ]
}