{
    "data": {
        "created_time": "2017-04-10T13:49:47+0000", 
        "id": "10154345508521729_196766650830181", 
        "message": "My computer was hacked and I freaked out worrying about my FB account on my IPhone so I deactivated it. I made a new FB account and lost all friends. I posted that I have new account so they're all getting new requests. Should deactivate the old, keep the new only or keep both?accounts?  I hate to lose all the old pics and comments? Thanks!!"
    }, 
    "reactions": {
        "angry": {
            "data": [], 
            "summary": {
                "total_count": 0
            }
        }, 
        "haha": {
            "data": [], 
            "summary": {
                "total_count": 0
            }
        }, 
        "like": {
            "data": [], 
            "summary": {
                "total_count": 2
            }
        }, 
        "love": {
            "data": [], 
            "summary": {
                "total_count": 0
            }
        }, 
        "sad": {
            "data": [], 
            "summary": {
                "total_count": 0
            }
        }, 
        "wow": {
            "data": [], 
            "summary": {
                "total_count": 0
            }
        }
    }, 
    "replies": [
        {
            "created_time": "2017-04-10T16:35:05+0000", 
            "id": "10154345508521729_1694464977520353", 
            "message": "Hi Jane. It's against the Facebook Community Standards to maintain more than one personal account. Learn more: http://bit.ly/2ojX5nt. -William"
        }, 
        {
            "created_time": "2017-09-30T20:30:57+0000", 
            "id": "10154345508521729_272916273199404", 
            "message": "Then why do you not let them enjoy that profile? Facebook you push people to where it's needed..."
        }, 
        {
            "created_time": "2017-09-30T20:34:06+0000", 
            "id": "10154345508521729_1971789513059423", 
            "message": "To explain is it's either you or metropolitan s who keep me going in circles. And Boone helps me to understand if by chance was me..."
        }
    ]
}