{
    "data": {
        "created_time": "2015-06-28T17:16:55+0000", 
        "id": "10152918539125079_10152918550100079", 
        "message": "I made this!!!!"
    }, 
    "reactions": {
        "angry": {
            "data": [], 
            "summary": {
                "total_count": 0
            }
        }, 
        "haha": {
            "data": [], 
            "summary": {
                "total_count": 0
            }
        }, 
        "like": {
            "data": [], 
            "summary": {
                "total_count": 33
            }
        }, 
        "love": {
            "data": [], 
            "summary": {
                "total_count": 0
            }
        }, 
        "sad": {
            "data": [], 
            "summary": {
                "total_count": 0
            }
        }, 
        "wow": {
            "data": [], 
            "summary": {
                "total_count": 0
            }
        }
    }, 
    "replies": [
        {
            "created_time": "2015-06-28T18:00:51+0000", 
            "id": "10152918539125079_10152918624895079", 
            "message": "Good for you xD"
        }, 
        {
            "created_time": "2015-06-28T22:41:46+0000", 
            "id": "10152918539125079_10152919100655079", 
            "message": "What's so special about it? Just edit the photo."
        }, 
        {
            "created_time": "2015-06-29T20:59:04+0000", 
            "id": "10152918539125079_10152921395570079", 
            "message": "That's what up!\nDope!"
        }, 
        {
            "created_time": "2016-08-12T10:38:31+0000", 
            "id": "10152918539125079_1247374711964008", 
            "message": ""
        }
    ]
}